simpledsa/__init__.py
simpledsa/priority_functions.py
simpledsa/priority_queue.py
simpledsa-0.2.1.dist-info/LICENSE
simpledsa-0.2.1.dist-info/METADATA
simpledsa-0.2.1.dist-info/WHEEL
simpledsa-0.2.1.dist-info/RECORD
