Metadata-Version: 2.1
Name: simpledsa
Version: 0.2.1
Summary: A simple and intuitive implementation of data structures and algorithms
Home-page: https://github.com/dsalathe/simpledsa
License: MIT
Keywords: data structures,algorithms,priority queue,heap
Author: David Salathé
Author-email: salathe.david@gmail.com
Requires-Python: >=3.8.1,<4.0
Classifier: Development Status :: 3 - Alpha
Classifier: Intended Audience :: Developers
Classifier: License :: OSI Approved :: MIT License
Classifier: Operating System :: OS Independent
Classifier: Programming Language :: Python :: 3
Classifier: Programming Language :: Python :: 3.9
Classifier: Programming Language :: Python :: 3.10
Classifier: Programming Language :: Python :: 3.11
Classifier: Programming Language :: Python :: 3.12
Classifier: Programming Language :: Python :: 3.13
Classifier: Programming Language :: Python :: 3.7
Classifier: Programming Language :: Python :: 3.8
Classifier: Topic :: Software Development :: Libraries :: Python Modules
Project-URL: Documentation, https://simpledsa.readthedocs.io
Project-URL: Repository, https://github.com/dsalathe/simpledsa
